{"files":{"plugins/openclaw/.turbo/turbo-build.log":{"size":38,"mtime_nanos":1774462675550434172,"mode":420,"is_dir":false},"plugins/openclaw/dist/index.d.ts":{"size":685,"mtime_nanos":1774462675523881155,"mode":420,"is_dir":false},"plugins/openclaw/dist":{"size":0,"mtime_nanos":0,"mode":0,"is_dir":true},"plugins/openclaw/dist/index.js":{"size":1190,"mtime_nanos":1774462675514194074,"mode":420,"is_dir":false}},"order":["plugins/openclaw/.turbo/turbo-build.log","plugins/openclaw/dist","plugins/openclaw/dist/index.d.ts","plugins/openclaw/dist/index.js"]}